treehopper/api/__init__.py
treehopper/api/device_commands.py
treehopper/api/find_boards.py
treehopper/api/i2c.py
treehopper/api/interfaces.py
treehopper/api/pin.py
treehopper/api/pwm.py
treehopper/api/settings.py
treehopper/api/spi.py
treehopper/api/treehopper_usb.py
treehopper/api/uart.py
treehopper/api/utility.py
treehopper/libraries/__init__.py
treehopper/libraries/flushable.py
treehopper/libraries/register_manager.py
treehopper/libraries/register_manager_adapter.py
treehopper/libraries/smbus_device.py
treehopper/libraries/smbus_register_manager_adapter.py
treehopper/libraries/spi_device.py
treehopper/utils/__init__.py
treehopper/utils/error.py
treehopper/utils/event_handler.py
treehopper/utils/utils.py
treehopper-1.13.0.dist-info/METADATA
treehopper-1.13.0.dist-info/WHEEL
treehopper-1.13.0.dist-info/top_level.txt
treehopper-1.13.0.dist-info/RECORD
