Metadata-Version: 2.1
Name: treehopper
Version: 1.13.0
Summary: Treehopper USB boards connect the physical world to your computer, smartphone, or tablet.
Home-page: https://treehopper.io
Author: Jay Carlson/Treehopper Electronics
Author-email: jay@treehopper.io
License: MIT license
Requires-Dist: pyusb
